langchain_exa/__init__.py
langchain_exa/_utilities.py
langchain_exa/py.typed
langchain_exa/retrievers.py
langchain_exa/tools.py
gigachain_exa-0.1.0.dist-info/LICENSE
gigachain_exa-0.1.0.dist-info/METADATA
gigachain_exa-0.1.0.dist-info/WHEEL
gigachain_exa-0.1.0.dist-info/RECORD
